vonage_http_client/__init__.py
vonage_http_client/_version.py
vonage_http_client/auth.py
vonage_http_client/errors.py
vonage_http_client/http_client.py
vonage_http_client-1.5.0.dist-info/METADATA
vonage_http_client-1.5.0.dist-info/WHEEL
vonage_http_client-1.5.0.dist-info/top_level.txt
vonage_http_client-1.5.0.dist-info/RECORD
