Metadata-Version: 2.1
Name: vonage-http-client
Version: 1.5.0
Summary: An HTTP client for making requests to Vonage APIs.
Author-email: Vonage <devrel@vonage.com>
Project-URL: Homepage, https://github.com/Vonage/vonage-python-sdk
Classifier: Programming Language :: Python
Classifier: Programming Language :: Python :: 3
Classifier: Programming Language :: Python :: 3.9
Classifier: Programming Language :: Python :: 3.10
Classifier: Programming Language :: Python :: 3.11
Classifier: Programming Language :: Python :: 3.12
Classifier: Programming Language :: Python :: 3.13
Classifier: License :: OSI Approved :: Apache Software License
Requires-Python: >=3.9
Requires-Dist: vonage-utils>=1.1.4
Requires-Dist: vonage-jwt>=1.1.5
Requires-Dist: requests>=2.27.0
Requires-Dist: typing-extensions>=4.9.0
Requires-Dist: pydantic>=2.9.2
